{
"vbvkfyqiscts5puaa66qjiex":["3tmaa","まひろ"],
"5wkkvwujlqalpwiy6653z7yx":["abcpodcast","🇬🇧Mr TMarsh-Connors 🇬🇧"],
"gfijale2wprvkdo56svizvc3":["atma","ātma"],
"3fak2ildjd7cxugvrhbnf3jf":["athunderheart","TMAC"],
"7nffl7frqfhuavvqhsdo5k22":["cjmack22","TMack"],
"mnno3vvboykfzuzi55mpck3c":["eserrouge","MarieTMallet"],
"osh2prgilhairyoz22owbgol":["johnnytman","PT: psycho tman"],
"mjgz4hm5zh4n5pkxddx4cyh6":["koraykayitmaz","Koray Kayıtmaz"],
"pnzbnoylookgu4fh4xghsq34":["lynda0507","LyndaGR8TMa💙"],
"l32qw3tzn4vez3wqhjzlif5x":["martinkoenigsberg","Martin Koenigsberg (MarTMar) (SteelyDab)"],
"sitn677fddyy75g47klkkogv":["maytree1","TMaibaum"],
"c6u23ijlm67gy5rv6id37pgb":["matmazeldecourton","MaTmazel"],
"ofvqzll2utbwhn3pbea2fukp":["magicsincetmac","MagicSinceTmac"],
"lacon7lnmt73hw35ifbnrbip":["n0tmaju","maju"],
"rfuvbzsz6xmkudac5smry7sl":["n0tmark","MØ"],
"asltrrxnw3flnomoacxaskpb":"ob4tman",
"ex5jgtexyjxgnlbbal54ekup":["ozzy2b1tmandias","Ozzy “2B1T” Mandias"],
"j6hs3s3yf6rtkolebeyrww4f":["psychelemental","j’anātman"],
"dxuce3dwldmjog2ov2cidivz":["soziales.thueringen.de","TMASGFF"],
"tbvgjiwp5edc5xlygitztqej":["sweett","TMac"],
"qq7gweqg6zx5idbdnkoa6biv":["t1tmaus","hailey copter"],
"4ejwuhvvv7fsmqt6zvlldxbl":["th3plan3tmars","Mars"],
"u6rw6hszidft62lib3dn5u6l":["thomasmcdonald","TMac"],
"6vxn46c22k6kpco2cujktoos":["tmanning","tmanning"],
"agg56lsoz3gbebtenqd3tyj7":["tmacailpein","Tòmas MacAilpein"],
"be7nlmdr7oun66adifyian6o":["tmarkos","TMarkos"],
"czodxnziuqm3qfzfhlkn5nuw":["tmark","tMark"],
"dqxsa5cjfrzulhalom4kuyd2":["tmaehara","™︎"],
"mahmqo4o3f7rteck4poq6h3e":["tmap","Tomas Apodaca "],
"z2nswr5u4quex4fsejssorh4":"tmagayon",
"nvni5lcngazcwjshkflbgope":["tmasada","Tomonari MASADA"],
"ryrsc7tbyifrkxzy3pxsq5wv":["tma","tma"],
"flhwsrbrg4iotrqwux3krddp":["tmattimore","Thomas Mattimore"],
"3wuaejflefaxrwtageed3iir":["tmac","tmac"],
"g5r77uw5a3vpubold6f2tqtb":["tmarthal.com","Tom Marthaler"],
"qja3lrkfuwo4gwoqubjr4leh":"tmatsu",
"3rsjjuspu4x5xouoojijt7hp":["tmarkovich","thomas markovich"],
"bwueom4lfhtzqsv2qaxqmkrr":["tmay","Thomas May"],
"u63lbpgerl2ojbv4i54nlj3g":["tmad","Theresa Maddix"],
"sgztplfa6q6n23nuqh5n3htk":["tmavuram","Tisya Mavuram"],
"gc7p6iffgk3n5ozhqimqa7oe":"tmater",
"7hfbp44lypn2tg4vosvlykm7":["tmau","Santos L Halper"],
"o6fevxgw43z3xrxmaeiim2gi":["tmaeee","Mae"],
"hj7e7u4zcgupgnsp2ijiebzl":["tmartens","Tim Martens"],
"clvdaa2bs6i4xxwidolp5tb4":["tmars","Thiago"],
"2gxqkzai52oadpj67ajcewxs":["tmatsubara","Takeshi Matsubara"],
"n6ofctu6jr6wivr5tcol5f6n":["tmagrino","Tom Magrino, PhD"],
"35mf7ix5duc4typvbek24yiv":["tmaaz","tmaaz ☕"],
"5uxqt65tkeisvzroncvzn4n3":["tman","Tommy"],
"raep3psvyzanbwgsap3gsclj":"tmasuhara",
"lfewharysosdtzy25kgvhf2v":["tmasat","マサト（ふ○まり）"],
"yxldppn73ztadab2t6jao3f2":["tmatk0723","💙슴사💙"],
"rp6zhnxc57zpvigqcsrwksgy":"tmahon",
"yr2w3yq2ftapge5qcjgevqvs":["tmask","Tmask"],
"2s75pd3zmeg4jjm2qzudjg5x":["tmatsuyama","シノダ"],
"wibtzeqtqqgvekw32bvoepfh":"tmannard",
"wfp6mia6cbmkyrjndqy3f5oa":["tmarsolais","Tim Marsolais "],
"hlkjaeipinioqblqlzdyghvy":["tmaes","Tom Maes"],
"4vy6uzyscfavysf5ljtxnbhx":["tmarczak","Tom Marczak"],
"qlnl2qwxu2sxzqjswjarsoi4":["tman69","Tman"],
"i6k6zoujpjr6ppnst6jvswue":"tmanewitz24",
"kzqjsolwqpibyzskwc2brveb":"tmalaher",
"vcv5elbrweymmbtphbpsdocm":["tmarsland","Tom "],
"f5rvejddt5rwypq25o7hv7jd":"tmatysik",
"naosehnjt6flnly2vz4hnbvm":["tmae","kk"],
"2jq4uydxeiome4mlkphtjsuk":"tmaskedwriter",
"anmcaudrlh5gzaighszu5vuw":["tmasu","まっすー"],
"jbfyxrgsqyj6dtovhamfrprq":["tmayo","T_May_O"],
"3cqpyxkhe457ly7xewlpeoiw":"tmago",
"wpbnmakoasw6hm263ddwjiul":"tmagaw",
"jnp52fyx4r2wxtfup7nqobx3":["tmarvan","Tomas Marvan"],
"zu2i35zdxnnpcowhsb7ox6lt":["tmanzella","Tim Manzella"],
"xr7mynchduff2jvrw26efvct":["tmar15","Tim Martin"],
"gnruxhiowrhjvor5vmqam75r":"tmargo101",
"7fzrodzlryq2my7ihjnirctt":"tmartintom",
"znm2mpef4boxiddu4l7y7trz":["tmasson","Tyler Masson"],
"bgqns52kdlk3d5puqizmcdmg":["tmalesys","Thomas Malesys"],
"tabbuullosakrzyqejy4id32":["tmaus84","Caede"],
"bjvckhhtpdjl2i64qabv3vi4":"tmaurel",
"tzrwj4jiziqwfyje6bxxseba":["tmawsm","Mae Torsion"],
"bd2rixdi6aqkx7w3gtybbooy":["tmarga","Marga"],
"flpyrlydmmns2bxhigbnwebi":["tmatsujp","T.Matsunaga"],
"yv7awwgkdmoyp5qua44ov3hb":"tmaslen",
"ypywhsk4ykhx5g2veqhws24m":"tmattevans",
"c3zi5twqwiiu353twzg63gc2":["tmakt","てむ"],
"e3sq53cprt6ugzx2udgwcewj":["tmadokafag","Breno Cop"],
"n545euha4kbq5b5bo2wsfqqv":["tmanatee","Tracy Mandel"],
"dtmvwedrcbf7f5qndsfqvh7w":"tmaenad",
"pj4kolwp4hmdfsmzj5u3wy6n":"tmac24679",
"bd3kacqa4cqbwfrow3zd3pua":["tmarloweauthor","Tom Marlowe"],
"mwpfz64bhcohkoiuh5lc4wwz":["tmariis","Eyes"],
"swhzpi2omb2orqoh2pjq6juy":["tmajor"," Tom"],
"74wiew5zk2judsfae7l24ase":["tmasrour","Tiago_"],
"vpofmuayi5kylntyltt6dxog":"tman14",
"ayhctdec3um3fozyhanpwr5t":"tmaj",
"7gdcmgtrgovlz2zoxn4wmknm":["tmascaro","TM71"],
"vygmvf772doinrxrec3r2jh3":"tmae36",
"tx2jhwwsgz73ab4ingmcq377":["tmahlmann","Trevor Mahlmann"],
"kwjcejucwnhicg2hxlgegv6f":["tmartin1438","Clever Name Not Found "],
"xfxcyn6vstjin53iqaagyjax":["tmane0","Griggz 🐲"],
"jx5h2s7upc2lada6fwe3qz7j":["tmarchand","Tara Marchand"],
"mwgg3cqhtkbzotvaewpyqxxu":"tmac24675",
"raihu6p34x3ae7krpx5tvz2w":"tmanti",
"nycwx2m5kzzqc5wgj5amdqgr":["tmack","Travis McNeill"],
"wutq3c5gtryxuq6qi6wmmi2j":"tmaster15",
"kuhqr2oghtd73bnruvl2bfeh":["tman2096","Tanner Pierce"],
"omwyjdkx52ppgkmbho5otako":"tmadted",
"ab36hvylc2vgepzg2vmdlg6z":"tmaster20",
"n635xpsohi4p5rvuegc5gtoe":["tmariethorn","TMarie Thorn "],
"w7x3dmtc56zu6nlmwywbehz3":["tmax","Tango / Max"],
"3ulehkvpfhbv3itqlaw6cyjj":["tmags","Trevor Magnani"],
"m67ivzprhdqvmrkt7fz2cu3i":"tmaulsby",
"ixzmvq3ciu6r6bclewjsx3t2":"tmanpdx",
"mk46ziac7wl7mnacvv2fb3jo":["tmarinko","Tina M"],
"aagauy3ufxbqrwx6vf5odwps":"tmaestro",
"ig2l74vwggsthtqcclye3afe":"tmart",
"bd5bbuyb7jogxs6g3cxaegku":"tmassassin16",
"pm2fh3nnfjogqhq5lq6gk2s4":["tmarkstahler","Thomas Markstahler"],
"37yvlzeuwokt3vsec7qdi4ud":"tmann",
"ivs2qbfvbcegpfygxtfqmjm5":["tmara","Ta Ma Ra"],
"tcg27gudhklyi3koyyzdp7pp":["tmacseatac","Tiffany McGuire"],
"4pnro5biwlpsjxyhhlfoagkg":["tmakamp","TM"],
"qve5quluknd7vc3uh7sgfj2x":["tmani","Máni"],
"dglc7nwjuubkarajohssvmui":["tmaedds","Canellems"],
"zbfijnhewc3bjhonxfenyhzq":["tmairhofer","Thomas Mairhofer"],
"ywqcasdokdx7aacufcslqalm":["tmariewms","Tanisha M. Williams "],
"cnx7gew26emjxryfcbrgg2w7":"tmacc829",
"cx6ejmkgivf275vdgxisn4xf":"tmaher",
"cy5lz2k32gv6lterj3l5gd3j":"tmannall",
"pk57wihf7tn54dm7chifhhxm":["tmas","Tuomas"],
"jw6shhp7n4rvyawd7rvbk5xw":["tmageofdemons","TmageOfdeMons"],
"y7lsaqees7plcmwyrup7lttg":["tmakinen","Toni Mäkinen"],
"wgxkrp7a55n2h6usolp6toyp":["tmalte","Mal.Te"],
"hwq6kaglddyedrw3aapxxws3":["tma26afn","みるく＊"],
"2axhoivf5y7oxrlm7lzlr3fq":"tmaynard",
"h3ni5vazo5hzgipdcfannrry":"tmartensson",
"sbmgxxruabkz5cyfhv7dasvv":"tmatta",
"k377aglhvvrwi7zozpdb3b3x":"tma-1",
"dt3qkwejdrgvwbu74ft7p2w4":"tman99",
"ion3qn4rjbpcum6myhqvjrcn":["tmackey","Theresa Mackey"],
"5mpkqrovkb4kgd4n2ua3y5bi":"tmakowka",
"lsyfjy4ya2maw4ckez536qvz":"tmayer",
"zewnxxnk5y2or2dbjcwi4vqm":"tmacsmash",
"zrqjzxsow7ifqmkkzuj3q2ff":"tmak",
"eqd44bnxlzxcd557w5ybnxnw":["txmxa","TMA"]
}
