{
"crhd67y2bstqrkaszjc735ih":["culturefrostfire52","TWC"],
"3gkngioy7isttv6q7xbigd6y":"mitsue3twcu",
"dgrjixfqov3spledyol7he6t":["travis.twchapman.com","travis"],
"awqndiu5w3qxhy73cpafmw6m":["twc","Tech Workers Coalition"],
"dkwrqribxotarbguxqd4gxei":["twcerveja","lai"],
"ntzicmn73ugauxzdyajht2ka":["twcarey","Theresa W. Carey"],
"6jj3iqkxiwkjcfie3gk2rxt5":["twccomms","Transformative Works and Cultures"],
"kcyqyl327hjogk2lgjjjlhor":["twcunningham","twcunningham"],
"hahszaatvuwf6hq5zfj2jgax":["twcarchive.com","TWC Archive"],
"d5byrprtvlca34p6ixfmeejg":["twcreech","Harpo "]
}
