{
"kdlvmvem2yt3cwcfitbjlqpf":["amirtzum","Amir Tzum "],
"j2aftwmlicnubl45frseasdf":["ayraki","Tzu"],
"arrkyblc5lfr2xy7myrtvkk3":["bobasquared","LeeTzui리수이🧋🍓"],
"fmrjfnt7ccahezsktfyj7lj4":["burnernhooch","Sun Tzudonym"],
"bwq5mvnhwjgvmtcgmzgid5l6":["cedarshihtzu","Cedar Shih Tzu"],
"pfrzyz4uo6yqvjal3jqthvfr":["dailydougie","Dougie the Shih Tzu"],
"e3uadrhmfdeu5nnsmgcrom4i":["graros","Bun Tzu's \"The Grart of War\""],
"4yns5omhhm5fbrias4j4wkxm":["henrytzu","Henry Tzu and mum"],
"gcdui5rt4ng6xp4u7f4vlwh7":["humunculitzu","Humunculi Tzu"],
"5tdvd7wqevdduhmy3g3ognv7":["maameakwaa","SassieTheShihTzu "],
"icbvsesj7vphj3b36br4axp3":["mingxitzu","MingxiTzu"],
"4jypxgbdylp7wokxzuzorrbp":["percybertie","Percy Bertie Tzu "],
"3gpj5ktjwaysffkl5x5wipt7":["sissyisembarrassed","Sissy Is Embarrassed By Shih Tzu Say"],
"7mdw7trdfn726ppdwmwtzbs3":["soontzu","Soon-Tzu Speechley 孫子"],
"4gwiaqwxao7vpbzaagmltflf":["sunnitzu","Sunny Bear - Sun Tzu"],
"ta7kuctmnw53xxx6y5lrsw6o":["theotzu","Theo Tzu"],
"io42chy3ugxtjdpvxq2rn3ak":["tskuo","Tzu-Sheng Kuo"],
"ckbfnndhxquhb2bf75vpqfha":["tzumao","Цзумао "],
"fyhmwiw3wec4cvl4c5r2scx4":["tzuzen","Susan TzuZen"],
"qj265yau3npfbaw2xbbdveue":["tzunlight","Nitida!!"],
"laxb7opln2pxik6c5iitaajc":["tzuyu"," "],
"t25k27ods4wykfzpbjt53ufy":["tzuicidios","mari"],
"7rmtat6w7ti3xfiv7xk72ywg":["tzuk","Josh Tzuker"],
"fd5sodj3xfzegq7lvuy5ifkt":["tzuforpeace","Tzu For Peace 📕"],
"xlnvl7yjw3oeucqnazu733op":"tzundoku",
"o7yrq5xpvw2s735wolocoy6b":"tzukru",
"hcf2x4hwchs54jy52kmp7uhp":"tzupancic",
"c3p3lklnswlp5kbwayrlvebz":"tzus",
"f4cjnfrfhc23qygyoux3ohtk":["tzuhi","츠히"],
"t3kfih67p6tzhn4kmrs7fwgn":["tzufit","tzufit"],
"3whw4kpmci3mxlv5b3cqvkzr":["tzuyuqi","𝓣."],
"6kyopv5tseow6ofp2vxanepn":["tzunamis","Brad"],
"e57zksnxcumolnuk6rx4rvir":["tzuki","Tzuki"],
"vhcalpeeneyh7o2hg5ugqf7o":["tzuyi","tzuyi"],
"3kxodoxjbbyzkbootmxgedhf":"tzu",
"2uq3lvxe5axb5ywnhn6vcxg4":["tzuchi","Tzu-Chi Yen"],
"m7c7fh2ybavebcimdiwjowbs":["tzurlab","Yonatan Tzur"],
"piuu2mimjnlwc2rrtskvixa4":["tzueee","蝴蝶和鳥"],
"basblh5jibe6f6zruigl3cwn":["tzuinte","쯔머"],
"37ya32oxqftmopmxpju7q4in":["tzuni26","Tzuni26"],
"p4h27w6bbgbbybnxnelzwsb2":["tzumukim","김쯤"]
}
