{
"ixmsqqj7fyvafjnbas2fv4fw":["c4tface","Cat Face"],
"okfojreuoiwg3vhgz7knvu26":["dunkman.tfatf.com","dunkman"],
"745ev74ldwvdqs62mun7kubs":["ibbitfaiye","İstanbul İtfaiyesi"],
"qusdn2yoglcu4dlpmrzju5eq":["tfasuka","神威飛鳥"],
"uluo4jijaf7q6mk4aubrq3yl":["tfandrer","LOKFÜHRERborusse"],
"mfevdhofv5ibx4mdnhlvgnlu":["tfa.ng","Tianyu Fang"],
"5wfw37c5sv2ytcwl2icduqrd":["tfa","Tfa"],
"lxgti574d466k246qolao7zm":"tfaal",
"63cd6n7iacsatcytmoulsbm5":"tfamanto",
"cucbj722gp3p6kjekktrjzur":["tfae","tfae"],
"m3oobcpllr2swzejfg7kqfsw":["tfantoine","Antoine Duval"],
"ma3vccwokmdinuvebo4qewcl":["tfandrade","Tiago Andrade"],
"gdhfirca63w2k2r5d4ryefky":"tfaass",
"bxdcgy72qhejnb75kp5rwrqw":["tfagl","TfagL - The Fifties & Gravity Laws "],
"24rhzi76dnhdo7kifj4ywdxr":["tfair1","Tay "],
"uo43z2qahdjqv3usbbddambb":["tfayne","Thomas Fayne"],
"ldpao3mymm6tecfdvgepylut":"tfarizla",
"mbtswf6uok2h3yc6c7b4p4lq":["tfarrpoetry","Thomas Farr"],
"ccl54hbjgpcecdzlyvpetrze":["tfanpage101","TFanPage101"],
"fiqml5nbvjfugwjipxlz2635":["tfannynob","Tiffany"],
"ahxdii7n47av24f6a6yg3bxh":"tfatf",
"lzsw7npn3scu7bbrrogimchf":["tfancs","T.F.A.N.C.S."],
"46jt3td3q7usicm3elz7navf":"tfa-tommy",
"qi27z7vby5apldhbor2wxywj":["theb0tfather","superbowl watcher"],
"2wp2yrc7toyydwdfd2gxdtfq":["tian","Do you mean @tfa.ng?"],
"pekcx54tajncja5ma4f74rh6":["who-tfay","✧ fay ✧"],
"hwevtduojkv55srua2he34ec":["z4tfa","SAFIT_TF 🇭🇳"]
}
