{
"iurmgzyc7ilcpqqcsv3viivp":["alexcs","Tdahto"],
"uf2c3ona5p7tt723komjw5zx":["stlcity-tda","Tim A"],
"4cqsxd2tp66cteznkbwr73bh":["tdaley","Trent Daley"],
"adlspc4a7ay4apgv7orpih6l":["tdawry","Travis Dawry"],
"lnclgq7lqrmxt6da7s57ver5":["tdakak","ただあき"],
"xhm4eadfsom5puvhj4jpfojq":["tdaleillustration","Tom Dale illustration"],
"ykbtgbwvqdupuo5yrqcspyrm":["tdaysiktak","세상에 이게 무슨 일이람"],
"6jmnu42j2dq226w3ml7m66uu":["tdags.io","Tim"],
"7j6q2rda5r722r7axwxdazbt":["tdaira","だいら / Tetsuya Odaira / 競走馬スタートアップCTO"],
"gzyhlyw2zd3snxw4fx6hpm2f":["tdanger19","Thomas Hamilton"],
"7oevggwwr4bvgrqck2qqrb5z":"tda",
"xpcvj6v2jyauyblh7tltfscp":["tdarkflame","Східняцьке бидло 💅"],
"yiw3brovj25gekrfstrrhfx3":["tdawgcincy","Tony Theobald"],
"pbocmtldv2ht5atcvafgoys7":"tda1",
"r2s5qx3v7h7npasst5ui5hgp":["tdarwin","Davin Taddeo"],
"jnslvaazr5zdpcbgrctbwto3":"tdalton",
"337vzzhn2tdstljy7gllk2cc":["tdaaron","Tom Aaron"],
"44zibm5qjcvtyura7piimgcd":["tdanielian","Thomas Danielian"],
"rsyqlrronaipdswseongwoiw":["tdam","Thomas MacKay"],
"re4unxgeqpd4dfvmdobinjw3":["tdaniel94","Thales"],
"43o33emu42adr3bn24o5jusl":["tdashy","Ty"],
"ujwfl24lxxmq2wkzm64z7vh5":["tdaigu","schönes Mädchen, böser Gott"],
"6elxqavjmbvotqqchljjrriz":"tdaloisio",
"5zitbrjn4y76e2reyrcnuevl":"tdaunt",
"oqvr6hrhtdjkire5ftrtg5q2":"tdawg",
"x2sirgncfqp3vws7z5nuol5i":["tdallman","Tim Dallman"],
"lioieokajzk5asef7jxfckgb":"tdaily",
"hf4br2fsnezersaohjv37tle":["tdammy92","Tdammy"],
"oxw4agu27jibfcgv75fw2x3u":"tdarknight",
"6zcuclhpjxnlrwwkomed52ur":["tdawks","Tom"],
"memi7yni7ipxfpwo5thljo66":["tdawghtx","Tdawg"],
"cl5cf3l7dpt7lccrjns5ufzw":["tdanna","Toby D’Anna"],
"6zi2obcfw4pummk7sgn6f73q":["tdambra","Todd D'Ambra"],
"cclsoytvocvteqr5hd52vora":["tdang","Tri Dang"],
"64cc5b22brrd3nyuacvjjzgo":"tda80",
"ne4kvd7wef64u6at3l22bh56":["tdaquino","Tony D'Aquino"],
"qt2ec24mofa66rfchwj25j6n":["tdavid93","Taylor Rhoades "],
"fj52cz6ij7utxhlz7qkzzzrf":["tdanielmorris","T. Daniel Morris"],
"3l25zfh7wfysxwrbgbjb5bww":["tdamienjd","Damien"],
"anzqcuars2n25k4vrrhq67yr":["tdart","emi the asset banshee"],
"pniyuvnly42fg5nx7rjwknsb":"tdaharsh",
"2ylrsb4ywqjtktdhatj25tua":"tdavis",
"enlwmsjqh4wdtmdjmyxi6c42":"tdarkshadow",
"2pddnkktachuekzqsihbulbd":["tdahfael","Rafael F."],
"mn3ayrykir5aqkltoc6vjnfw":["tdawgmcfadden","Terence McFadden"],
"t4pvy2t7vdjqvatoxjrp5ltw":["tdah","Squirrel rápida"],
"7dasjqlqicazqbw3suqtlggh":"tdavis234",
"bzvgvgh5ms4ldeaa434nurew":"tdanielmidgley",
"tf3uwp6dtycbvj4bgejtrt3u":["tdarcillon","Thibault Darcillon"],
"esasg3yhuc43dx2cyefncdct":["tdans","tdans"],
"zjevj5dqaclqhkvpeb5ymhls":["tdavis11","Nurseasaurus"],
"ti7wromjgpyar3owcih5hiln":"tdag",
"ufyjprf3vffxcnwgz3ydtffk":["tdalameda","TomDon Alameda"],
"2pnr7ojnceuallgnfrtttxou":["thef4tdaddy","Ed David "],
"qrhrno37naqrgexfbd4heiir":["tribotdah","Tribo TDAH® - Apoia.se/TriboTDAH"],
"uygmbys5pglrt7ronnbqyi4f":["yagorinaldi","A bicha com TDAH"]
}
