{
"ozifc4vnuwcaypjcyu3mlryl":["bankaitcg","GBankaiTCG"],
"pkmsvosj26juftqm7jjom3ld":["cqe","Eileen, TcgTisms Haver"],
"a4rb7kzmmkl7mkboqkkfpw3n":["evo10tcg","evoten"],
"6s6ykhn25hrzkily6lqjnc6a":["grolorktcg","GrolorkTCG"],
"xqaniue7rrtonzgzdxvj3xwa":["hardleyharlequin","Harley☆TCG(They/Them)"],
"z6dkqznqqd36opaelnwc4qqv":["littletroubles","Little Troubles TCG"],
"3jr7nrg37lviabx7o7thansg":["mazetcg","MazeTCG"],
"nqlr7o2quabbklglj5biypw3":["neverenderstcg","NEVERENDERS TCG"],
"itcgesz73pbwtdggcpf2sbao":["optimisttcg","OptimistTCG"],
"yvyaasfaiq4nwbl3iw3o4lwz":["tcgproto","proto"],
"z5mym32lkwhxi73gu3gntcyg":["rikkatakanashi","[Chuuni Clan] RikkaTCG (Rikka Theorycrafting)"],
"7urfptiet5rsvlbtgj6soyk4":["spellarms","SpellArms TCG"],
"yjwarb24vnxmvvf7qkahh6qu":["tcgdave","TCG Dave 🎲 🔜 Master Peace to 1"],
"wyh4lrpcyqhq6mlztjtirkew":"tcg",
"ixpfbzii4y5m3pgwvfuiw66l":"tcgreene",
"a5phtrhsad23s45b6ofhlumz":"tcgiv",
"pfd6m4ds2xc327a7sgz53jq7":["tcgreen","TCGreen"],
"kq5ngrbpseg7vwyy4lgcrglc":["tcgo","Thiago Calfa "],
"jx2qtdcwsm7w2oonp5lmtfv2":["tcgs","TCGS"],
"bnekt5sreagkmj3zvkuuxgh3":"tcgtrainerkris",
"ftol2bgf6lqnypyagtntp6gj":["tcgravy","Distracted Yeti"],
"cuou5pmjuhqy73bgko3ytbyu":["tcgfatih","Yakup Yusuf Kuyucu"],
"myjepuw3tkihs6woxzz424yl":["tcgm","TCGM"],
"g7vd5uoja5t4bmtnfnveqwgh":["tcgreenwood","Tammy C. Greenwood"],
"6f2vr7tj7kcoquxcfeopglm3":["tcgmicah","TcgMicah"],
"lpmpbkasatrdgr5zzyngwa3f":"tcgrsl",
"qkyqpr7ngz2255nbjs7libnv":["tcgamerboy2002","TCgamerboy2002"],
"lyhj73sobazfkazzdzg74u2o":"tcgamer",
"yvcp5ymxjkjkopiq6pyobu66":"tcgtally",
"qopsa3kb34a7hwbizvb33vaq":["thattcgguy","ThatTCGGuy"],
"irzueyoy3aqcnf4pcr3sdjnc":["thetrainingcourt","The Training Court TCG"],
"bist3pf7gwxiloofmy7lypiy":["thecraftyghost","TCGhost"],
"7ym5n653bl4x7s3k4lsat7jr":["thiccboitcg","Thicc Boi TCG"],
"lsic6e4ub76o4oya5htua3k7":["trinitynova","Trinity Nova | TCG Streamer"],
"3k55sa2dyjmq57h275uuw5zq":["waifus.de","Waifu TCG"],
"2bk5mb6jyjapuq5vo6d3u47w":["xanshil","Amelia - Local Trans TCG seller"],
"kpsfl2aiu6fdgqxmedtsz4rv":["zubatcg","Zuba ★ TCG"]
}
